apk_signer/__init__.py
apk_signer/apksigner.py
apk_signer/config.py
apk_signer/pyapksigner.jks
apk_signer/scripts/__init__.py
apk_signer/scripts/launcher.py
apk_signer-1.1.3.dist-info/LICENSE
apk_signer-1.1.3.dist-info/METADATA
apk_signer-1.1.3.dist-info/WHEEL
apk_signer-1.1.3.dist-info/entry_points.txt
apk_signer-1.1.3.dist-info/top_level.txt
apk_signer-1.1.3.dist-info/RECORD
