Metadata-Version: 2.1
Name: apk-signer
Version: 1.1.3
Summary: Sign the apk file
Home-page: https://github.com/ksg97031/apk-signer
Author: ksg97031
Author-email: ksg97031@gmail.com
Classifier: Programming Language :: Python :: 3
Classifier: License :: OSI Approved :: MIT License
Classifier: Operating System :: OS Independent
Requires-Python: >=3.5
License-File: LICENSE
Requires-Dist: click
Requires-Dist: androguard
